beginai/__init__.py
beginai/conn/__init__.py
beginai/conn/mqtt.py
beginai/exec/__init__.py
beginai/exec/execute_compute.py
beginai/exec/remote_compute.py
beginai/exec/embeddings/__init__.py
beginai/exec/embeddings/apply.py
beginai/exec/embeddings/master.py
beginai/exec/embeddings/worker.py
beginai/exec/embeddings/instructions/__init__.py
beginai/exec/embeddings/instructions/boolean.py
beginai/exec/embeddings/instructions/category.py
beginai/exec/embeddings/instructions/date.py
beginai/exec/embeddings/instructions/interaction.py
beginai/exec/embeddings/instructions/location.py
beginai/exec/embeddings/instructions/number.py
beginai/exec/embeddings/instructions/parser.py
beginai/exec/embeddings/instructions/text.py
beginai/exec/embeddings/instructions/utils.py
beginai/exec/embeddings/instructions/deep_text/__init__.py
beginai/exec/embeddings/instructions/deep_text/bpe.py
beginai/orchapi/__init__.py
beginai/orchapi/api.py
beginai/storage/__init__.py
beginai/storage/s3.py
beginai/storage/sqllite.py
beginai/tests/__init__.py
beginai/tests/exec/__init__.py
beginai/tests/exec/embeddings/__init__.py
beginai/tests/exec/embeddings/apply_test.py
beginai/tests/exec/embeddings/mock_service.py
beginai/tests/exec/embeddings/worker_methods_session.py
beginai/tests/exec/embeddings/worker_methods_validation_interaction_attributes_test.py
beginai/tests/exec/embeddings/worker_methods_validation_interaction_test.py
beginai/tests/exec/embeddings/worker_methods_validation_labels_test.py
beginai/tests/exec/embeddings/worker_methods_validation_object_test.py
beginai/tests/exec/embeddings/worker_methods_validation_user_test.py
beginai/tests/exec/embeddings/worker_test.py
beginai/tests/exec/embeddings/instructions/__init__.py
beginai/tests/exec/embeddings/instructions/boolean_test.py
beginai/tests/exec/embeddings/instructions/category_test.py
beginai/tests/exec/embeddings/instructions/date_test.py
beginai/tests/exec/embeddings/instructions/interaction_test.py
beginai-2.2.1.dist-info/LICENSE.txt
beginai-2.2.1.dist-info/METADATA
beginai-2.2.1.dist-info/WHEEL
beginai-2.2.1.dist-info/top_level.txt
beginai-2.2.1.dist-info/RECORD
