Metadata-Version: 2.1
Name: beginai
Version: 2.2.1
Summary: A library to interact with Begin AI platform in order to build personalisation algorithms.
Home-page: https://docs.begin.ai
Author: Begin AI Research & Engineering
Author-email: engineering@begin.ai
License: Proprietary
Platform: UNKNOWN
Classifier: Programming Language :: Python :: 3
Classifier: Operating System :: OS Independent
Requires-Python: >=3.6
Requires-Dist: requests ==2.27.1
Requires-Dist: tqdm
Requires-Dist: pytest
Requires-Dist: freezegun
Requires-Dist: pandas
